nanograph/__init__.py
nanograph-0.0.1.dist-info/METADATA
nanograph-0.0.1.dist-info/WHEEL
nanograph-0.0.1.dist-info/licenses/LICENSE
nanograph-0.0.1.dist-info/RECORD
